Metadata-Version: 2.1
Name: flashrag-dev
Version: 0.1.2
Summary: A library for efficient Retrieval-Augmented Generation research
Home-page: https://github.com/RUC-NLPIR/FlashRAG
Author: Jiajie Jin, Yutao Zhu, Chenghao Zhang, Xinyu Yang, Zhicheng Dou
Author-email: jinjiajie@ruc.edu.cn
License: MIT License
Requires-Python: >=3.9
License-File: LICENSE
Requires-Dist: datasets
Requires-Dist: base58
Requires-Dist: nltk
Requires-Dist: numpy
Requires-Dist: openai
Requires-Dist: peft
Requires-Dist: PyYAML
Requires-Dist: rank-bm25
Requires-Dist: rouge
Requires-Dist: spacy>=3.6.1
Requires-Dist: tiktoken
Requires-Dist: torch
Requires-Dist: tqdm
Requires-Dist: transformers>=4.40.0
Requires-Dist: bm25s[full]
Requires-Dist: fschat
Requires-Dist: streamlit
Provides-Extra: core
Requires-Dist: datasets; extra == "core"
Requires-Dist: base58; extra == "core"
Requires-Dist: nltk; extra == "core"
Requires-Dist: numpy; extra == "core"
Requires-Dist: openai; extra == "core"
Requires-Dist: peft; extra == "core"
Requires-Dist: PyYAML; extra == "core"
Requires-Dist: rank-bm25; extra == "core"
Requires-Dist: rouge; extra == "core"
Requires-Dist: spacy>=3.6.1; extra == "core"
Requires-Dist: tiktoken; extra == "core"
Requires-Dist: torch; extra == "core"
Requires-Dist: tqdm; extra == "core"
Requires-Dist: transformers>=4.40.0; extra == "core"
Requires-Dist: bm25s[full]; extra == "core"
Requires-Dist: fschat; extra == "core"
Requires-Dist: streamlit; extra == "core"
Provides-Extra: full
Requires-Dist: datasets; extra == "full"
Requires-Dist: base58; extra == "full"
Requires-Dist: nltk; extra == "full"
Requires-Dist: numpy; extra == "full"
Requires-Dist: openai; extra == "full"
Requires-Dist: peft; extra == "full"
Requires-Dist: PyYAML; extra == "full"
Requires-Dist: rank-bm25; extra == "full"
Requires-Dist: rouge; extra == "full"
Requires-Dist: spacy>=3.6.1; extra == "full"
Requires-Dist: tiktoken; extra == "full"
Requires-Dist: torch; extra == "full"
Requires-Dist: tqdm; extra == "full"
Requires-Dist: transformers>=4.40.0; extra == "full"
Requires-Dist: bm25s[full]; extra == "full"
Requires-Dist: fschat; extra == "full"
Requires-Dist: streamlit; extra == "full"
Requires-Dist: pyserini; extra == "full"
Requires-Dist: sentence-transformers>=3.0.1; extra == "full"
Requires-Dist: vllm>=0.4.1; extra == "full"
Provides-Extra: generator
Requires-Dist: vllm>=0.4.1; extra == "generator"
Provides-Extra: retriever
Requires-Dist: pyserini; extra == "retriever"
Requires-Dist: sentence-transformers>=3.0.1; extra == "retriever"
